{
    "LeagueName": "BMGC VI (ID# 197497)",
    "SeasonYear": "2011",
    "Week": "14",
    "LeftTeam": {
        "Manager": "",
        "TeamName": "Philadelphia Pride",
        "Players": [
            {
                "FullName": "Colt McCoy",
                "PlayerId": 24060,
                "MatchupPosition": "QB",
                "PointsScored": 5.86,
                "ProjectedPoints": 9,
                "ShortName": "C. McCoy",
                "Stats": [
                    {
                        "StatText": "209 Passing Yards",
                        "Points": 8.36
                    },
                    {
                        "StatText": "2 Interceptions",
                        "Points": -4
                    },
                    {
                        "StatText": "15 Rushing Yards",
                        "Points": 1.5
                    }
                ]
            },
            {
                "FullName": "Dwayne Bowe",
                "PlayerId": 8277,
                "MatchupPosition": "WR",
                "PointsScored": 6.9,
                "ProjectedPoints": 7.03,
                "ShortName": "D. Bowe",
                "Stats": [
                    {
                        "StatText": "69 Reception Yards",
                        "Points": 6.9
                    }
                ]
            },
            {
                "FullName": "Nate Washington",
                "PlayerId": 7492,
                "MatchupPosition": "WR",
                "PointsScored": 19,
                "ProjectedPoints": 6.38,
                "ShortName": "N. Washington",
                "Stats": [
                    {
                        "StatText": "130 Reception Yards",
                        "Points": 13
                    },
                    {
                        "StatText": "1 Reception Touchdowns",
                        "Points": 6
                    }
                ]
            },
            {
                "FullName": "Rashard Mendenhall",
                "PlayerId": 8800,
                "MatchupPosition": "RB",
                "PointsScored": 7.6,
                "ProjectedPoints": 15.46,
                "ShortName": "R. Mendenhall",
                "Stats": [
                    {
                        "StatText": "76 Rushing Yards",
                        "Points": 7.6
                    }
                ]
            },
            {
                "FullName": "Reggie Bush",
                "PlayerId": 7751,
                "MatchupPosition": "RB",
                "PointsScored": 13,
                "ProjectedPoints": 12.66,
                "ShortName": "R. Bush",
                "Stats": [
                    {
                        "StatText": "103 Rushing Yards",
                        "Points": 10.3
                    },
                    {
                        "StatText": "27 Reception Yards",
                        "Points": 2.7
                    }
                ]
            },
            {
                "FullName": "Vernon Davis",
                "PlayerId": 7755,
                "MatchupPosition": "TE",
                "PointsScored": 3.2,
                "ProjectedPoints": 7.93,
                "ShortName": "V. Davis",
                "Stats": [
                    {
                        "StatText": "32 Reception Yards",
                        "Points": 3.2
                    }
                ]
            },
            {
                "FullName": "Percy Harvin",
                "PlayerId": 9286,
                "MatchupPosition": "W/R",
                "PointsScored": 16.9,
                "ProjectedPoints": 11.12,
                "ShortName": "P. Harvin",
                "Stats": [
                    {
                        "StatText": "40 Rushing Yards",
                        "Points": 4
                    },
                    {
                        "StatText": "69 Reception Yards",
                        "Points": 6.9
                    },
                    {
                        "StatText": "1 Reception Touchdowns",
                        "Points": 6
                    }
                ]
            },
            {
                "FullName": "Josh Scobee",
                "PlayerId": 6896,
                "MatchupPosition": "K",
                "PointsScored": 5,
                "ProjectedPoints": 7.38,
                "ShortName": "J. Scobee",
                "Stats": [
                    {
                        "StatText": "5 Point After Attempt Made",
                        "Points": 5
                    }
                ]
            },
            {
                "FullName": "Green Bay",
                "PlayerId": 100009,
                "MatchupPosition": "DEF",
                "PointsScored": 18,
                "ProjectedPoints": 13.01,
                "ShortName": "G. Bay",
                "Stats": [
                    {
                        "StatText": "1 Sack",
                        "Points": 1
                    },
                    {
                        "StatText": "4 Interception",
                        "Points": 8
                    },
                    {
                        "StatText": "1 Fumble Recovery",
                        "Points": 2
                    },
                    {
                        "StatText": "1 Touchdown",
                        "Points": 6
                    },
                    {
                        "StatText": "1 Points Allowed 14-20 points",
                        "Points": 1
                    }
                ]
            },
            {
                "FullName": "Mike Vick",
                "PlayerId": 5448,
                "MatchupPosition": "BN",
                "PointsScored": 11.22,
                "ProjectedPoints": 16.99,
                "ShortName": "M. Vick",
                "Stats": [
                    {
                        "StatText": "208 Passing Yards",
                        "Points": 8.32
                    },
                    {
                        "StatText": "1 Passing Touchdowns",
                        "Points": 4
                    },
                    {
                        "StatText": "1 Interceptions",
                        "Points": -2
                    },
                    {
                        "StatText": "9 Rushing Yards",
                        "Points": 0.9
                    }
                ]
            },
            {
                "FullName": "Deion Branch",
                "PlayerId": 5951,
                "MatchupPosition": "BN",
                "PointsScored": 0,
                "ProjectedPoints": 6.67,
                "ShortName": "D. Branch",
                "Stats": []
            },
            {
                "FullName": "Ben Watson",
                "PlayerId": 6791,
                "MatchupPosition": "BN",
                "PointsScored": 1.1,
                "ProjectedPoints": 3.71,
                "ShortName": "B. Watson",
                "Stats": [
                    {
                        "StatText": "11 Reception Yards",
                        "Points": 1.1
                    }
                ]
            },
            {
                "FullName": "Earnest Graham",
                "PlayerId": 7108,
                "MatchupPosition": "BN",
                "PointsScored": 0,
                "ProjectedPoints": 0,
                "ShortName": "E. Graham",
                "Stats": []
            },
            {
                "FullName": "Eli Manning",
                "PlayerId": 6760,
                "MatchupPosition": "BN",
                "PointsScored": 26.8,
                "ProjectedPoints": 16.1,
                "ShortName": "E. Manning",
                "Stats": [
                    {
                        "StatText": "400 Passing Yards",
                        "Points": 16
                    },
                    {
                        "StatText": "BONUS: Passing Yards > 350",
                        "Points": 5
                    },
                    {
                        "StatText": "2 Passing Touchdowns",
                        "Points": 8
                    },
                    {
                        "StatText": "1 Interceptions",
                        "Points": -2
                    },
                    {
                        "StatText": "-2 Rushing Yards",
                        "Points": -0.2
                    }
                ]
            },
            {
                "FullName": "Buffalo",
                "PlayerId": 100002,
                "MatchupPosition": "BN",
                "PointsScored": 11,
                "ProjectedPoints": 8,
                "ShortName": "B.",
                "Stats": [
                    {
                        "StatText": "2 Sack",
                        "Points": 2
                    },
                    {
                        "StatText": "1 Fumble Recovery",
                        "Points": 2
                    },
                    {
                        "StatText": "1 Touchdown",
                        "Points": 6
                    },
                    {
                        "StatText": "1 Block Kick",
                        "Points": 2
                    },
                    {
                        "StatText": "1 Points Allowed 28-34 points",
                        "Points": -1
                    }
                ]
            }
        ]
    },
    "RightTeam": {
        "Manager": "Tyler G",
        "TeamName": "Not Last",
        "Players": [
            {
                "FullName": "Joe Flacco",
                "PlayerId": 8795,
                "MatchupPosition": "QB",
                "PointsScored": 15.08,
                "ProjectedPoints": 12.86,
                "Stats": [
                    {
                        "StatText": "227 Passing Yards",
                        "Points": 9.08
                    },
                    {
                        "StatText": "2 Passing Touchdowns",
                        "Points": 8
                    },
                    {
                        "StatText": "1 Interceptions",
                        "Points": -2
                    }
                ]
            },
            {
                "FullName": "DeSean Jackson",
                "PlayerId": 8826,
                "MatchupPosition": "WR",
                "PointsScored": 11.9,
                "ProjectedPoints": 5.52,
                "Stats": [
                    {
                        "StatText": "59 Reception Yards",
                        "Points": 5.9
                    },
                    {
                        "StatText": "1 Reception Touchdowns",
                        "Points": 6
                    }
                ]
            },
            {
                "FullName": "Nate Burleson",
                "PlayerId": 6407,
                "MatchupPosition": "WR",
                "PointsScored": 2.6,
                "ProjectedPoints": 6.42,
                "Stats": [
                    {
                        "StatText": "1 Rushing Yards",
                        "Points": 0.1
                    },
                    {
                        "StatText": "25 Reception Yards",
                        "Points": 2.5
                    }
                ]
            },
            {
                "FullName": "Marion Barber",
                "PlayerId": 7285,
                "MatchupPosition": "RB",
                "PointsScored": 18,
                "ProjectedPoints": 8.18,
                "Stats": [
                    {
                        "StatText": "108 Rushing Yards",
                        "Points": 10.8
                    },
                    {
                        "StatText": "1 Rushing Touchdowns",
                        "Points": 6
                    },
                    {
                        "StatText": "32 Reception Yards",
                        "Points": 3.2
                    },
                    {
                        "StatText": "1 Fumbles Lost",
                        "Points": -2
                    }
                ]
            },
            {
                "FullName": "John Kuhn",
                "PlayerId": 7695,
                "MatchupPosition": "RB",
                "PointsScored": 4.6,
                "ProjectedPoints": 2.69,
                "Stats": [
                    {
                        "StatText": "46 Rushing Yards",
                        "Points": 4.6
                    }
                ]
            },
            {
                "FullName": "Jake Ballard",
                "PlayerId": 24550,
                "MatchupPosition": "TE",
                "PointsScored": 11.2,
                "ProjectedPoints": 4.85,
                "Stats": [
                    {
                        "StatText": "52 Reception Yards",
                        "Points": 5.2
                    },
                    {
                        "StatText": "1 Reception Touchdowns",
                        "Points": 6
                    }
                ]
            },
            {
                "FullName": "Santana Moss",
                "PlayerId": 5463,
                "MatchupPosition": "W/R",
                "PointsScored": 14.1,
                "ProjectedPoints": 8.65,
                "Stats": [
                    {
                        "StatText": "81 Reception Yards",
                        "Points": 8.1
                    },
                    {
                        "StatText": "1 Reception Touchdowns",
                        "Points": 6
                    }
                ]
            },
            {
                "FullName": "Stephen Gostkowski",
                "PlayerId": 7867,
                "MatchupPosition": "K",
                "PointsScored": 10,
                "ProjectedPoints": 11.16,
                "Stats": [
                    {
                        "StatText": "2 Field Goals 20-29 Yards",
                        "Points": 6
                    },
                    {
                        "StatText": "4 Point After Attempt Made",
                        "Points": 4
                    }
                ]
            },
            {
                "FullName": "Detroit",
                "PlayerId": 100008,
                "MatchupPosition": "DEF",
                "PointsScored": 27,
                "ProjectedPoints": 12.47,
                "Stats": [
                    {
                        "StatText": "4 Sack",
                        "Points": 4
                    },
                    {
                        "StatText": "3 Interception",
                        "Points": 6
                    },
                    {
                        "StatText": "3 Fumble Recovery",
                        "Points": 6
                    },
                    {
                        "StatText": "2 Touchdown",
                        "Points": 12
                    },
                    {
                        "StatText": "1 Points Allowed 28-34 points",
                        "Points": -1
                    }
                ]
            },
            {
                "FullName": "James Jones",
                "PlayerId": 8332,
                "MatchupPosition": "BN",
                "PointsScored": 2.9,
                "ProjectedPoints": 5.34,
                "Stats": [
                    {
                        "StatText": "29 Reception Yards",
                        "Points": 2.9
                    }
                ]
            },
            {
                "FullName": "Donald Driver",
                "PlayerId": 4863,
                "MatchupPosition": "BN",
                "PointsScored": 7.5,
                "ProjectedPoints": 3.35,
                "Stats": [
                    {
                        "StatText": "75 Reception Yards",
                        "Points": 7.5
                    }
                ]
            },
            {
                "FullName": "Peyton Hillis",
                "PlayerId": 9004,
                "MatchupPosition": "BN",
                "PointsScored": 2.5,
                "ProjectedPoints": 6.02,
                "Stats": [
                    {
                        "StatText": "25 Rushing Yards",
                        "Points": 2.5
                    }
                ]
            },
            {
                "FullName": "Matt Hasselbeck",
                "PlayerId": 4416,
                "MatchupPosition": "BN",
                "PointsScored": 1.76,
                "ProjectedPoints": 11.26,
                "Stats": [
                    {
                        "StatText": "44 Passing Yards",
                        "Points": 1.76
                    }
                ]
            },
            {
                "FullName": "Darren McFadden",
                "PlayerId": 8781,
                "MatchupPosition": "BN",
                "PointsScored": 0,
                "ProjectedPoints": 0,
                "Stats": []
            },
            {
                "FullName": "Denver",
                "PlayerId": 100007,
                "MatchupPosition": "BN",
                "PointsScored": 10,
                "ProjectedPoints": 14.2,
                "Stats": [
                    {
                        "StatText": "4 Sack",
                        "Points": 4
                    },
                    {
                        "StatText": "1 Fumble Recovery",
                        "Points": 2
                    },
                    {
                        "StatText": "1 Points Allowed 7-13 points",
                        "Points": 4
                    }
                ]
            }
        ]
    }
}